django_telegrambot/__init__.py
django_telegrambot/admin.py
django_telegrambot/apps.py
django_telegrambot/models.py
django_telegrambot/tests.py
django_telegrambot/urls.py
django_telegrambot/views.py
django_telegrambot/management/__init__.py
django_telegrambot/management/commands/__init__.py
django_telegrambot/management/commands/botpolling.py
django_telegrambot/static/css/django_telegrambot.css
django_telegrambot/static/js/django_telegrambot.js
django_telegrambot/templates/django_telegrambot/base.html
django_telegrambot/templates/django_telegrambot/index.html
django_telegrambot-1.0.0.dist-info/DESCRIPTION.rst
django_telegrambot-1.0.0.dist-info/METADATA
django_telegrambot-1.0.0.dist-info/RECORD
django_telegrambot-1.0.0.dist-info/WHEEL
django_telegrambot-1.0.0.dist-info/metadata.json
django_telegrambot-1.0.0.dist-info/top_level.txt
