Metadata-Version: 2.0
Name: django-telegrambot
Version: 1.0.0
Summary: A simple app to develop Telegram bot with Django
Home-page: https://github.com/JungDev/django-telegrambot
Author: django-telegrambot
Author-email: francesco.scarlato@gmail.com
License: BSD
Keywords: django-telegrambot
Platform: UNKNOWN
Classifier: Development Status :: 4 - Beta
Classifier: Framework :: Django
Classifier: Framework :: Django :: 1.7
Classifier: Framework :: Django :: 1.8
Classifier: Intended Audience :: Developers
Classifier: License :: OSI Approved :: BSD License
Classifier: Natural Language :: English
Classifier: Programming Language :: Python :: 2
Classifier: Programming Language :: Python :: 2.7
Classifier: Programming Language :: Python :: 3
Classifier: Programming Language :: Python :: 3.3
Classifier: Programming Language :: Python :: 3.4
Classifier: Programming Language :: Python :: 3.5
Requires-Dist: python-telegram-bot
